odoo/addons/mrp_analytic_cost/README.rst
odoo/addons/mrp_analytic_cost/__init__.py
odoo/addons/mrp_analytic_cost/__manifest__.py
odoo/addons/mrp_analytic_cost/i18n/hu.po
odoo/addons/mrp_analytic_cost/i18n/mrp_analytic_cost.pot
odoo/addons/mrp_analytic_cost/i18n/mrp_analytic_cost_material.pot
odoo/addons/mrp_analytic_cost/models/__init__.py
odoo/addons/mrp_analytic_cost/models/account_analytic_line.py
odoo/addons/mrp_analytic_cost/models/mrp_production.py
odoo/addons/mrp_analytic_cost/models/mrp_workorder.py
odoo/addons/mrp_analytic_cost/models/stock_move.py
odoo/addons/mrp_analytic_cost/readme/CONFIGURATION.rst
odoo/addons/mrp_analytic_cost/readme/CONTRIBUTORS.rst
odoo/addons/mrp_analytic_cost/readme/DESCRIPTION.rst
odoo/addons/mrp_analytic_cost/readme/USAGE.rst
odoo/addons/mrp_analytic_cost/static/description/icon.png
odoo/addons/mrp_analytic_cost/static/description/index.html
odoo/addons/mrp_analytic_cost/views/account_analytic_line_view.xml
odoo/addons/mrp_analytic_cost/views/mrp_production_views.xml
odoo/addons/mrp_analytic_cost/views/mrp_workcenter_view.xml
odoo14_addon_mrp_analytic_cost-14.0.1.1.0.dist-info/METADATA
odoo14_addon_mrp_analytic_cost-14.0.1.1.0.dist-info/WHEEL
odoo14_addon_mrp_analytic_cost-14.0.1.1.0.dist-info/top_level.txt
odoo14_addon_mrp_analytic_cost-14.0.1.1.0.dist-info/RECORD
